frame_ble/__init__.py
frame_ble/frame_ble.py
frame_ble-1.1.1.dist-info/METADATA
frame_ble-1.1.1.dist-info/WHEEL
frame_ble-1.1.1.dist-info/licenses/LICENSE
frame_ble-1.1.1.dist-info/RECORD
