Metadata-Version: 2.4
Name: frame-ble
Version: 1.1.1
Summary: Low-level library for Bluetooth LE connection to Brilliant Labs Frame
Project-URL: Homepage, https://github.com/CitizenOneX/frame_ble_python
Project-URL: Documentation, https://frame-ble-python.readthedocs.io/en/latest/index.html
Project-URL: Bug Tracker, https://github.com/CitizenOneX/frame_ble_python/issues
Project-URL: Changelog, https://github.com/CitizenOneX/frame_ble_python/blob/main/CHANGELOG.md
Author: CitizenOne
License-File: LICENSE
Classifier: License :: OSI Approved :: BSD License
Classifier: Operating System :: OS Independent
Classifier: Programming Language :: Python :: 3
Requires-Python: >=3.7
Requires-Dist: bleak>=0.22.3
